{
  "_class": "shapeGroup",
  "booleanOperation": -1,
  "clippingMaskMode": 0,
  "do_objectID": "96E0A3A9-8C92-4ECC-AEC5-E643360A4A5D",
  "exportOptions": {
    "_class": "exportOptions",
    "do_objectID": "3CFCCE8C-039A-4B8E-858A-D69F55B6B64A",
    "exportFormats": [
    ],
    "includedLayerIds": [
    ],
    "layerOptions": 0,
    "shouldTrim": false
  },
  "frame": {
    "_class": "rect",
    "constrainProportions": false,
    "do_objectID": "EA8DD710-8513-4AE5-880C-7E5BBA1B08C2",
    "height": 6,
    "width": 0.666666666666667,
    "x": 7.666666666666668,
    "y": 8
  },
  "hasClickThrough": false,
  "hasClippingMask": false,
  "isFixedToViewport": false,
  "isFlippedHorizontal": false,
  "isFlippedVertical": false,
  "isLocked": false,
  "isVisible": true,
  "layerListExpandedType": 0,
  "layers": [
    {
      "class": "shapePath",
      "id": "2427FED2-EA2B-41D2-9F71-9B1A5140EC07"
    }
  ],
  "name": "Icon Path",
  "nameIsFixed": false,
  "resizingConstraint": 63,
  "resizingType": 0,
  "rotation": 0,
  "shouldBreakMaskChain": false,
  "style": {
    "_class": "style",
    "borderOptions": {
      "_class": "borderOptions",
      "dashPattern": [
      ],
      "do_objectID": "CE75BD4C-94D5-459E-8C67-1A493F624734",
      "isEnabled": false,
      "lineCapStyle": 1,
      "lineJoinStyle": 1
    },
    "borders": [
      {
        "_class": "border",
        "color": {
          "_class": "color",
          "alpha": 1,
          "blue": 1,
          "green": 0.9647092332210473,
          "red": 0.9416158536585366
        },
        "fillType": 0,
        "isEnabled": true,
        "position": 0,
        "thickness": 2
      }
    ],
    "do_objectID": "966BFF92-7186-42CA-984C-325D60201AA2",
    "endMarkerType": 0,
    "miterLimit": 10,
    "startMarkerType": 0,
    "windingRule": 1
  },
  "windingRule": 1
}