{
  "_class": "shapePath",
  "booleanOperation": -1,
  "clippingMaskMode": 0,
  "do_objectID": "AB1FC348-53AB-41CC-9F1B-CE0CFB01DD8C",
  "edited": true,
  "exportOptions": {
    "_class": "exportOptions",
    "do_objectID": "2C295117-29E7-439C-96EF-272766798F12",
    "exportFormats": [
    ],
    "includedLayerIds": [
    ],
    "layerOptions": 0,
    "shouldTrim": false
  },
  "frame": {
    "_class": "rect",
    "constrainProportions": false,
    "do_objectID": "18948FCA-1862-46CB-9A4A-3E0DA6AA7F22",
    "height": 3.333333333333334,
    "width": 0.666666666666667,
    "x": 7.666666666666668,
    "y": 2
  },
  "hasClippingMask": false,
  "isClosed": false,
  "isFixedToViewport": false,
  "isFlippedHorizontal": false,
  "isFlippedVertical": false,
  "isLocked": false,
  "isVisible": true,
  "layerListExpandedType": 0,
  "name": "Icon Path",
  "nameIsFixed": false,
  "pointRadiusBehaviour": 1,
  "points": [
    {
      "_class": "curvePoint",
      "cornerRadius": 0,
      "curveFrom": "{0.5, 1}",
      "curveMode": 1,
      "curveTo": "{0.5, 1}",
      "hasCurveFrom": false,
      "hasCurveTo": false,
      "point": "{0.5, 1}"
    },
    {
      "_class": "curvePoint",
      "cornerRadius": 0,
      "curveFrom": "{0.5, 0}",
      "curveMode": 1,
      "curveTo": "{0.5, 0}",
      "hasCurveFrom": false,
      "hasCurveTo": false,
      "point": "{0.5, 0}"
    }
  ],
  "resizingConstraint": 63,
  "resizingType": 0,
  "rotation": 0,
  "shouldBreakMaskChain": false,
  "style": {
    "_class": "style",
    "borderOptions": {
      "_class": "borderOptions",
      "dashPattern": [
      ],
      "do_objectID": "42959A32-5C7C-4C93-980B-9969CE1B029E",
      "isEnabled": false,
      "lineCapStyle": 1,
      "lineJoinStyle": 1
    },
    "borders": [
      {
        "_class": "border",
        "color": {
          "_class": "color",
          "alpha": 1,
          "blue": 1,
          "green": 0.9647092332210473,
          "red": 0.9416158536585366
        },
        "fillType": 0,
        "isEnabled": true,
        "position": 0,
        "thickness": 2
      }
    ],
    "do_objectID": "1ADE73EA-C91B-4C01-8222-27641CE431D4",
    "endMarkerType": 0,
    "miterLimit": 10,
    "startMarkerType": 0,
    "windingRule": 1
  }
}