{
  "_class": "shapeGroup",
  "booleanOperation": -1,
  "clippingMaskMode": 0,
  "do_objectID": "0AEC96C0-0330-40AF-B2A9-0CC7B0456D09",
  "exportOptions": {
    "_class": "exportOptions",
    "do_objectID": "40B158C8-1FDD-4B8F-AB9D-EA204BA761F6",
    "exportFormats": [
    ],
    "includedLayerIds": [
    ],
    "layerOptions": 0,
    "shouldTrim": false
  },
  "frame": {
    "_class": "rect",
    "constrainProportions": false,
    "do_objectID": "D97AC98F-0BC4-42CC-AF29-2B4CA5F2210B",
    "height": 11.8875,
    "width": 12.5,
    "x": 1.25,
    "y": 1.25
  },
  "hasClickThrough": false,
  "hasClippingMask": false,
  "isFixedToViewport": false,
  "isFlippedHorizontal": false,
  "isFlippedVertical": false,
  "isLocked": false,
  "isVisible": true,
  "layerListExpandedType": 0,
  "layers": [
    {
      "class": "shapePath",
      "id": "BBEAF638-D68E-47F9-8390-7EF1BE8CD489"
    }
  ],
  "name": "Icon Path",
  "nameIsFixed": false,
  "resizingConstraint": 63,
  "resizingType": 0,
  "rotation": 0,
  "shouldBreakMaskChain": false,
  "style": {
    "_class": "style",
    "borderOptions": {
      "_class": "borderOptions",
      "dashPattern": [
      ],
      "do_objectID": "4661CDD4-7CF3-418D-BC23-8C68DAB4F8EC",
      "isEnabled": false,
      "lineCapStyle": 1,
      "lineJoinStyle": 1
    },
    "borders": [
      {
        "_class": "border",
        "color": {
          "_class": "color",
          "alpha": 1,
          "blue": 0.4908030310718783,
          "green": 0.8363449304049697,
          "red": 0.9954144021739131
        },
        "fillType": 0,
        "isEnabled": true,
        "position": 0,
        "thickness": 2
      }
    ],
    "do_objectID": "28A76E77-727B-43C7-BD26-04219C2DDD2D",
    "endMarkerType": 0,
    "fills": [
      {
        "_class": "fill",
        "color": {
          "_class": "color",
          "alpha": 1,
          "blue": 0.4901960784313726,
          "green": 0.8352941176470589,
          "red": 0.996078431372549
        },
        "fillType": 0,
        "isEnabled": true,
        "noiseIndex": 0,
        "noiseIntensity": 0,
        "patternFillType": 1,
        "patternTileScale": 1
      }
    ],
    "miterLimit": 10,
    "startMarkerType": 0,
    "windingRule": 1
  },
  "windingRule": 1
}