{
  "_class": "group",
  "booleanOperation": 0,
  "do_objectID": "D5322D6D-7FB0-4C51-9267-C034DC6EDA36",
  "exportOptions": {
    "_class": "exportOptions",
    "exportFormats": [
    ],
    "includedLayerIds": [
    ],
    "layerOptions": 0,
    "shouldTrim": false
  },
  "frame": {
    "_class": "rect",
    "constrainProportions": true,
    "height": 11,
    "width": 25,
    "x": 336,
    "y": 18
  },
  "hasClickThrough": false,
  "isFixedToViewport": false,
  "isFlippedHorizontal": false,
  "isFlippedVertical": false,
  "isLocked": false,
  "isVisible": true,
  "layerListExpandedType": 0,
  "layers": [
    {
      "class": "shapeGroup",
      "id": "09A9FEBE-E500-4913-BB9C-BB17C0581210"
    },
    {
      "class": "shapeGroup",
      "id": "E3BB779C-ACC4-4ED4-81D6-ED9BF4F69997"
    },
    {
      "class": "shapeGroup",
      "id": "B948B681-9840-4A91-A912-AE09005552C1"
    }
  ],
  "name": "Battery",
  "nameIsFixed": true,
  "resizingConstraint": 44,
  "resizingType": 0,
  "rotation": 0,
  "shouldBreakMaskChain": false,
  "style": {
    "_class": "style",
    "endMarkerType": 0,
    "miterLimit": 10,
    "startMarkerType": 0,
    "windingRule": 1
  }
}